mysql_to_mongo
