Metadata-Version: 2.1
Name: mysql-to-mongo
Version: 1.0.3
Summary: Migrate your MySql databse to MongoDb.
Home-page: UNKNOWN
Author: ArJun Gawali
Author-email: arjungawali111@gmail.com
License: MIT
Keywords: mysql-to-mongodb,migrate,mysql,mongodb
Platform: UNKNOWN
Classifier: Development Status :: 5 - Production/Stable
Classifier: Intended Audience :: Education
Classifier: Operating System :: Microsoft :: Windows :: Windows 10
Classifier: Operating System :: Unix
Classifier: Operating System :: MacOS :: MacOS X
Classifier: License :: OSI Approved :: MIT License
Classifier: Programming Language :: Python :: 3
